fileconfig/__init__.py
fileconfig/bases.py
fileconfig/meta.py
fileconfig/stack.py
fileconfig/tools.py
fileconfig-0.6.1.dist-info/LICENSE.txt
fileconfig-0.6.1.dist-info/METADATA
fileconfig-0.6.1.dist-info/WHEEL
fileconfig-0.6.1.dist-info/top_level.txt
fileconfig-0.6.1.dist-info/RECORD
