Metadata-Version: 2.1
Name: fileconfig
Version: 0.6.1
Summary: Config file sections as objects
Home-page: https://github.com/xflr6/fileconfig
Author: Sebastian Bank
Author-email: sebastian.bank@uni-leipzig.de
License: MIT
Project-URL: Issue Tracker, https://github.com/xflr6/fileconfig/issues
Project-URL: CI, https://github.com/xflr6/fileconfig/actions
Project-URL: Coverage, https://codecov.io/gh/xflr6/fileconfig
Keywords: configuration ini file inheritance aliasing
Platform: any
Classifier: Development Status :: 4 - Beta
Classifier: Intended Audience :: Developers
Classifier: License :: OSI Approved :: MIT License
Classifier: Operating System :: OS Independent
Classifier: Programming Language :: Python :: 3
Classifier: Programming Language :: Python :: 3.7
Classifier: Programming Language :: Python :: 3.8
Classifier: Programming Language :: Python :: 3.9
Classifier: Programming Language :: Python :: 3.10
Requires-Python: >=3.7
License-File: LICENSE.txt
Provides-Extra: dev
Requires-Dist: tox (>=3) ; extra == 'dev'
Requires-Dist: flake8 ; extra == 'dev'
Requires-Dist: pep8-naming ; extra == 'dev'
Requires-Dist: wheel ; extra == 'dev'
Requires-Dist: twine ; extra == 'dev'
Provides-Extra: test
Requires-Dist: pytest (>=7) ; extra == 'test'
Requires-Dist: pytest-cov ; extra == 'test'
